Metadata-Version: 1.1
Name: pmr2.oauth
Version: 0.6.1
Summary: OAuth PAS Plugin, OAuth 1.0 provider for Plone.
Home-page: https://github.com/PMR2/pmr2.oauth
Author: Tommy Yu
Author-email: tommy.yu@auckland.ac.nz
License: GPL
Platform: UNKNOWN
Classifier: Development Status :: 4 - Beta
Classifier: Programming Language :: Python
Classifier: Framework :: Plone :: 4.0
Classifier: Framework :: Plone :: 4.1
Classifier: Framework :: Plone :: 4.2
Classifier: License :: OSI Approved :: GNU General Public License v2 (GPLv2)
Classifier: Programming Language :: Python :: 2.5
Classifier: Programming Language :: Python :: 2.6
Classifier: Programming Language :: Python :: 2.7
Classifier: Topic :: Software Development :: Libraries :: Python Modules
